pytket_pecos/__init__.py
pytket_pecos/emulator.py
pytket_pecos-0.3.1.dist-info/licenses/LICENSE
pytket_pecos-0.3.1.dist-info/WHEEL
pytket_pecos-0.3.1.dist-info/METADATA
pytket_pecos-0.3.1.dist-info/RECORD
