Metadata-Version: 2.4
Name: pytket_pecos
Version: 0.3.1
Summary: This package enables emulation of pytket circuits using the PECOS emulator.
Author-email: Alec Edgington <alec.edgington@quantinuum.com>
Classifier: License :: OSI Approved :: Apache Software License
Classifier: Programming Language :: Python :: 3.10
Classifier: Programming Language :: Python :: 3.11
Classifier: Programming Language :: Python :: 3.12
Classifier: Programming Language :: Python :: 3.13
Classifier: Programming Language :: Python :: 3.14
Classifier: Operating System :: POSIX :: Linux
Classifier: Operating System :: MacOS :: MacOS X
Classifier: Operating System :: Microsoft :: Windows
License-File: LICENSE
Requires-Dist: pytket >=2.11.0
Requires-Dist: pytket-phir >=0.10.1
Requires-Dist: quantum-pecos[wasmtime] >=0.8.0.dev0
Project-URL: Home, https://github.com/CQCL/pytket-pecos
